chatlabs_support/__init__.py
chatlabs_support/chatlabs_aiogram_support/__init__.py
chatlabs_support/chatlabs_aiogram_support/dialogs/__init__.py
chatlabs_support/chatlabs_aiogram_support/dialogs/api.py
chatlabs_support/chatlabs_aiogram_support/dialogs/create_ticket/__init__.py
chatlabs_support/chatlabs_aiogram_support/dialogs/create_ticket/confirm.py
chatlabs_support/chatlabs_aiogram_support/dialogs/create_ticket/enter_text.py
chatlabs_support/chatlabs_aiogram_support/dialogs/create_ticket/enter_title.py
chatlabs_support/chatlabs_aiogram_support/dialogs/states.py
chatlabs_support/chatlabs_aiogram_support/dialogs/support/__init__.py
chatlabs_support/chatlabs_aiogram_support/dialogs/support/close_tickets.py
chatlabs_support/chatlabs_aiogram_support/dialogs/support/main.py
chatlabs_support/chatlabs_aiogram_support/dialogs/support/open_tickets.py
chatlabs_support/chatlabs_aiogram_support/dialogs/support/ticket_details.py
chatlabs_support/chatlabs_aiogram_support/dialogs/support/utils.py
chatlabs_support/chatlabs_aiogram_support/settings.py
chatlabs_support/chatlabs_django_support/__init__.py
chatlabs_support/chatlabs_django_support/admin.py
chatlabs_support/chatlabs_django_support/apps.py
chatlabs_support/chatlabs_django_support/consumers.py
chatlabs_support/chatlabs_django_support/filters.py
chatlabs_support/chatlabs_django_support/migrations/0001_initial.py
chatlabs_support/chatlabs_django_support/migrations/__init__.py
chatlabs_support/chatlabs_django_support/models.py
chatlabs_support/chatlabs_django_support/routing.py
chatlabs_support/chatlabs_django_support/serializers.py
chatlabs_support/chatlabs_django_support/signals.py
chatlabs_support/chatlabs_django_support/templates/support/support_manager.html
chatlabs_support/chatlabs_django_support/urls.py
chatlabs_support/chatlabs_django_support/views.py
chatlabs_support/exceptions.py
chatlabs_support/utils.py
chatlabs_support-0.1.5.dist-info/METADATA
chatlabs_support-0.1.5.dist-info/WHEEL
chatlabs_support-0.1.5.dist-info/RECORD
