Metadata-Version: 2.3
Name: chatlabs-support
Version: 0.1.5
Summary: 
Author: Rostislaww
Author-email: rostiki.com@mail.ru
Requires-Python: >=3.11,<4.0
Classifier: Programming Language :: Python :: 3
Classifier: Programming Language :: Python :: 3.11
Classifier: Programming Language :: Python :: 3.12
Classifier: Programming Language :: Python :: 3.13
Provides-Extra: chatlabs-aiogram-support
Provides-Extra: chatlabs-django-support
Requires-Dist: aiogram (>=3.16.0,<4.0.0) ; extra == "chatlabs-aiogram-support"
Requires-Dist: aiogram-dialog (>=2.3.0,<3.0.0) ; extra == "chatlabs-aiogram-support"
Requires-Dist: channels (>=4.2.0,<5.0.0) ; extra == "chatlabs-django-support"
Requires-Dist: daphne (>=4.1.2,<5.0.0) ; extra == "chatlabs-django-support"
Requires-Dist: django (==5.0.1) ; extra == "chatlabs-django-support"
Requires-Dist: django-filter (>=24.3,<25.0) ; extra == "chatlabs-django-support"
Requires-Dist: djangorestframework (>=3.15.2,<4.0.0) ; extra == "chatlabs-django-support"
Project-URL: Homepage, https://github.com/RostHarcha/chatlabs-support
